{"object":{"id":"860394","dataset":"gminy","object_id":"1006","data":{"powiaty.sejm_okreg_id":"10","nazwa_urzedu":"Gmina Lgota Wielka","wydatki_roczne":"13474523.25","teryt":"101208","id":"1006","powierzchnia":"63.00","nts":"1101712082","szef_stanowisko_id":"3","nazwa":"Lgota Wielka","zadluzenie_roczne":"262051.13","dochody_roczne":"13212472.12","powiaty.nazwa":"radomszcza\u0144ski","fax":"(0-44) 680 17 77","adres":"ul. Radomszcza\u0144ska 60\n97-565 Lgota Wielka","wojewodztwa.id":"5","telefon":"(0-44) 680 13 81","typ_nazwa":"Gmina wiejska","powiat_id":"252","wojewodztwa.nazwa":"\u0141\u00f3dzkie","bip_www":"lgota.i-bip.pl\/index.php?lang=1&cat=2","liczba_ludnosci":4381,"typ_id":"2","wojewodztwo_id":"5","email":"lgota@i-bip.pl","powiaty.id":"252","rada_nazwa":"Rada Gminy w Lgocie Wielkiej"},"score":1,"layers":{"enspat":{"ADD":["qemwHuf`uB|VneAyDb]hV`cAfk@tp@f|@~QiFd{A`J~GaTbkBfN~LwYzjA}NfxAze@mHtDpIfiBtb@hg@kyCroAq`ChgAdJjlA_Ulk@snG~b@ikBagDu{B}KhVek@u_Ak^pFoYi`A}k@y]ie@zfDiiAu@fFeC`Bgc@qFvSs_@uz@bA{_@eZuqA_DiiBud@uv@{@jGnStkAkTzc@uFgKqOhFhOzMlAnJ_L~E|Txz@_GrTl_@jrAwWdaAuI{SkEhUog@`i@sGp_@"],"DIFF":[]},"rada_komitety":null,"wskazniki":null,"radni_powiazania":null,"szef":null,"ostatnie_posiedzenie":null,"dzielnice":null,"dataset":null}}}