{"object":{"id":"860420","dataset":"gminy","object_id":"1032","data":{"powiaty.sejm_okreg_id":"17","nazwa_urzedu":"Urz\u0105d Miasta i Gminy w Lipsku","wydatki_roczne":"25091588.74","teryt":"140903","id":"1032","powierzchnia":"135.00","nts":"1142709033","szef_stanowisko_id":"1","nazwa":"Lipsko","zadluzenie_roczne":"-1798901.98","dochody_roczne":"26890490.72","powiaty.nazwa":"lipski","fax":"0-48 378-00-48","adres":"27-300 Lipsko, ul. 1 Maja 2","wojewodztwa.id":"7","telefon":"0-48 378-00-48","typ_nazwa":"Gmina miejsko-wiejska","powiat_id":"144","wojewodztwa.nazwa":"Mazowieckie","bip_www":"www.lipsko.bip.info.pl","liczba_ludnosci":11639,"typ_id":"3","wojewodztwo_id":"7","email":"info@lipsko.home.pl","powiaty.id":"144","rada_nazwa":"Rada Miejska w Lipsku"},"score":1,"layers":{"enspat":{"ADD":["srtwHs`icC`k@_FmBngArJ~SaIdu@zdApGqFfTzYvYaCtj@bIhIdJksA~b@lHI|aEqGvJd]jYcMlhBhSIiCn\\bI|Mwa@fmA_ApcAa[|fB|aAthAoEp~@dGfyB`_@kAhg@eByFukBdlDyCdRihCt@hXfNlF|vBnXni@wr@wKoP_Rt^g^rLrI{pBfkAbEN`Wtm@|o@cPfg@pr@hu@iFjs@hShUfb@iuGzj@ocDdUc^`Y`NzSmu@P}^tc@~kA|CoDtH}RuNeI}Ek~@|Ou{A_Q{rApi@ey@qt@oeD|m@gg@lBcXoj@ro@sz@l`@}u@~_DaJzI{u@aj@wVw`@o{@{^cp@kJma@fIqWwRgL~HkSbKmVcEie@}fAu_@wNqw@bM_}@ze@aRy\\_Fyi@`A_LhTyInHbMdIyDqSks@|Qsh@{KmsA~FwJwNqUgDuh@eNmGvD~Joh@vaAe{@nu@}Lof@rG_Gyf@}nBvRmQaVmKcPbnArQhkA{n@ba@eQ}Kgo@n}BaV}DwEy\\mIjEgEzoA"],"DIFF":[]},"rada_komitety":null,"wskazniki":null,"radni_powiazania":null,"szef":null,"ostatnie_posiedzenie":null,"dzielnice":null,"dataset":null}}}