{"object":{"id":"860423","dataset":"gminy","object_id":"1035","data":{"powiaty.sejm_okreg_id":"15","nazwa_urzedu":"Urz\u0105d Gminy Lisia G\u00f3ra","wydatki_roczne":"40525810.91","teryt":"121603","id":"1035","powierzchnia":"105.00","nts":"2122416032","szef_stanowisko_id":"3","nazwa":"Lisia G\u00f3ra","zadluzenie_roczne":"2727099.07","dochody_roczne":"37798711.84","powiaty.nazwa":"tarnowski","fax":"0-14 678-42-49","adres":"33-140 Lisia G\u00f3ra, ul. 1 Maja 7","wojewodztwa.id":"6","telefon":"0-14 678-42-49","typ_nazwa":"Gmina wiejska","powiat_id":"320","wojewodztwa.nazwa":"Ma\u0142opolskie","bip_www":"www.malopolska.pl\/bip\/lisia+gora","liczba_ludnosci":14389,"typ_id":"2","wojewodztwo_id":"6","email":"nowak@lisiagora.tarnow.pl","powiaty.id":"320","rada_nazwa":"Rada Gminy Lisia G\u00f3ra"},"score":1,"layers":{"enspat":{"ADD":["wmaqHmib`ChiAz_Chi@l^|L}EtVg}@lr@oMnGbpEhCncAqPzhAfq@r_CtCdi@gX~rBeC|_Aa\\_NdMh{@yg@vk@_TyFuP~p@hUzo@rc@{H|Mz_@AtZgMPX`Vl^tJ_WzIrXjK_AhLnH~B{Bpj@uM^q@`LrGvmAwC|iAbq@t_@t{@mT~`AzBxd@}TfD{_@n`@mo@pk@j@rGyz@}DmqAxPgUc@aPyOyI?qm@|Oo|AbGsGbn@hYd@mnAyH~@aAob@|Loh@df@qBkl@szBgDkaChL}^oa@kiDu^bNsMe}@qKbD{Aef@hJc_@gPwLcAy[wVEkKyQdZyBtWabCaF{ThCk_@e@cb@uMgBcJcb@{OlEkK{UaOIgKrChIp}@s`Axv@ca@grFk`@byAad@gMeb@h}@kd@kXmFq\\lEcc@wGp@wAwVqo@zvIk_@mFSaMmJ}CuDog@qL{InJohAm[qbAkLsCe^`qC"],"DIFF":[]},"rada_komitety":null,"wskazniki":null,"radni_powiazania":null,"szef":null,"ostatnie_posiedzenie":null,"dzielnice":null,"dataset":null}}}