{"object":{"id":"860461","dataset":"gminy","object_id":"1073","data":{"powiaty.sejm_okreg_id":"21","nazwa_urzedu":"Urz\u0105d Gminy Lubsza","wydatki_roczne":"21340765.34","teryt":"160105","id":"1073","powierzchnia":"212.00","nts":"5163101052","szef_stanowisko_id":"3","nazwa":"Lubsza","zadluzenie_roczne":"-424007.07","dochody_roczne":"21764772.41","powiaty.nazwa":"brzeski","fax":"0-77 411-86-30","adres":"49-313 Lubsza, ul. Brzeska 16","wojewodztwa.id":"8","telefon":"0-77 411-86-30","typ_nazwa":"Gmina wiejska","powiat_id":"23","wojewodztwa.nazwa":"Opolskie","bip_www":"bip.lubsza.tensoft.pl","liczba_ludnosci":8998,"typ_id":"2","wojewodztwo_id":"8","email":"lubsza@lubsza.ug.gov.pl","powiaty.id":"23","rada_nazwa":"Rada Gminy Lubsza"},"score":1,"layers":{"enspat":{"ADD":["u{gvH{najBfo@lQlDkJfKzXnAvQuFfBtP~gBwG~tAuXf_@n[`t@~Ro\\Dmy@|_@g~@rl@xIjQlVu@d[cMpKgFeJiNhRhVziEgg@v^~g@jvA`\\lsBznA_Nfs@xP~MeEjAkTve@kYvv@x]zJ|WlNbEn`@cJjGw]nMtl@pXlJjEgaAtLob@nw@kL~k@qn@xaA`FnTwIbJkHyD}Hdj@qbBy`@oWvXmhAf^`_@rUc^jKA~Zmq@jTidAjZoaEuLuj@as@kj@qLgc@fBmj@hPyWUym@|Uiq@{Bwo@}Su|@lNk\\]{Wm]x~@oRs\\b@_ZqR{@wD_MjLggAvO|O}Fyh@pOmkAuB{QaeBvj@oNesAgP|Qws@wd@lAxLiGpBp@sVua@gWvD_SiO`GxIee@cSkMtSad@}\\yXx\\wt@yX{b@aGnOk^cWiFdi@qVrToKeTwO~S{Gys@aa@ze@{Qri@eHr\\bJxh@eDxD_cAy{@kUyAXpTe}@d\\aRpr@_p@pe@edAseA}HnQ_R_Mec@|kA|Kx_@tNdG}Ptb@|^|Q{@fPoYnnAmB`oA}Jbk@uh@`~@`qArTvXhk@|Crc@mJ`VfAkUkRf@`Fvh@{^|~@q\\bKsEyc@i\\zKzBxTqNvm@cY`G{FpX"],"DIFF":[]},"rada_komitety":null,"wskazniki":null,"radni_powiazania":null,"szef":null,"ostatnie_posiedzenie":null,"dzielnice":null,"dataset":null}}}