{"object":{"id":"860544","dataset":"gminy","object_id":"1155","data":{"powiaty.sejm_okreg_id":"25","nazwa_urzedu":"Urz\u0105d Miasta Malborka","wydatki_roczne":"97176163.62","teryt":"220901","id":"1155","powierzchnia":"17.00","nts":"6224209011","szef_stanowisko_id":"1","nazwa":"Malbork","zadluzenie_roczne":"1813535.15","dochody_roczne":"95362628.47","powiaty.nazwa":"malborski","fax":"0-55 647-23-24","adres":"82-200 Malbork Plac S\u0142owia\u0144ski","wojewodztwa.id":"11","telefon":"0-55 647-99-00","typ_nazwa":"Gmina miejska","powiat_id":"166","wojewodztwa.nazwa":"Pomorskie","bip_www":"www.bip.malbork.pl","liczba_ludnosci":39387,"typ_id":"1","wojewodztwo_id":"11","email":"piotrs@um.malbork.pl","powiaty.id":"166","rada_nazwa":"Rada Miasta Malborka"},"score":1,"layers":{"enspat":{"ADD":["g}{hI}fasBtOdbAnn@lo@x^}tCvg@x^rk@f_AxeA`f@`Jl[vSs`A{ZyMr_@q~BaV_OtNmmAgbBatAqXvAg\\go@vEmu@{S_Cq@qlBcAjUiOtScLeGuEjw@c{@l_ByIls@jBfaAvi@`vAqo@hmA"],"DIFF":[]},"rada_komitety":null,"wskazniki":null,"radni_powiazania":null,"szef":null,"ostatnie_posiedzenie":null,"dzielnice":null,"dataset":null}}}