{"object":{"id":"860832","dataset":"gminy","object_id":"1443","data":{"powiaty.sejm_okreg_id":"34","nazwa_urzedu":"Urz\u0105d Miasta Ostr\u00f3da","wydatki_roczne":"128155073.86","teryt":"281501","id":"1443","powierzchnia":"14.00","nts":"6285415011","szef_stanowisko_id":"1","nazwa":"Ostr\u00f3da","zadluzenie_roczne":"16004726.08","dochody_roczne":"112150347.78","powiaty.nazwa":"ostr\u00f3dzki","fax":"0-89 642-94-01","adres":"14-100 Ostr\u00f3da ul. Mickiewicza 24","wojewodztwa.id":"14","telefon":"0-89 642-94-00","typ_nazwa":"Gmina miejska","powiat_id":"213","wojewodztwa.nazwa":"Warmi\u0144sko-mazurskie","bip_www":"www.bipostroda.24.pl","liczba_ludnosci":34060,"typ_id":"1","wojewodztwo_id":"14","email":"piotr@um.ostroda.pl","powiaty.id":"213","rada_nazwa":"Rada Miejska w Ostr\u00f3dzie"},"score":1,"layers":{"enspat":{"ADD":["_`|fIuuvxBfR~`@vSl@jAnRhm@ym@zH~T`JsIdFnVfn@pLbLn`AmDzu@lNbeAdGdCvDm@eRkrCjQeMs@wTjOyRxg@_Gme@aFe@w_@sRiPxA}NdR}HqCcTzNoOq@yw@`F_CsHwVfl@sfCwHcc@uMdGc~@jvAiP{r@ab@_@pGn]oMv|@mJsEzEwb@yFap@guAuHkK`r@pJ`hBgNp\\v@|oAgKxd@"],"DIFF":[]},"rada_komitety":null,"wskazniki":null,"radni_powiazania":null,"szef":null,"ostatnie_posiedzenie":null,"dzielnice":null,"dataset":null}}}