{"object":{"id":"860831","dataset":"gminy","object_id":"1444","data":{"powiaty.sejm_okreg_id":"34","nazwa_urzedu":"Urz\u0105d Gminy Ostr\u00f3da","wydatki_roczne":"49954159.98","teryt":"281509","id":"1444","powierzchnia":"401.00","nts":"6285415092","szef_stanowisko_id":"3","nazwa":"Ostr\u00f3da","zadluzenie_roczne":"863562.86","dochody_roczne":"49090597.12","powiaty.nazwa":"ostr\u00f3dzki","fax":"0-89 646-29-45","adres":"14-100 Ostr\u00f3da, ul. Mickiewicza 24","wojewodztwa.id":"14","telefon":"0-89 646-32-81","typ_nazwa":"Gmina wiejska","powiat_id":"213","wojewodztwa.nazwa":"Warmi\u0144sko-mazurskie","bip_www":"www.ugostroda.24.pl","liczba_ludnosci":15834,"typ_id":"2","wojewodztwo_id":"14","email":"sekretariat@gminaostroda.pl","powiaty.id":"213","rada_nazwa":"Rada Gminy Ostr\u00f3da"},"score":1,"layers":{"enspat":{"ADD":["u|dgIizwxBlQrSbv@tSsNbsBeOtxBtpAr[dTgHrc@|RxC`QkJzIhJnL`OlG|KaNyFzw@zfCfg@j_@ye@xEmZhl@ym@lf@_HpFvhAaVzzAzE`b@pi@tcAuSl_AfIb}@oKdYtBdy@|^rr@xDdo@wGdjA~LfGb\\gk@kBgZ~h@zAjP_\\fIvBbSvk@jQrHtN`l@nWhEIrPbPbFxS~`@l^zH~m@vl@H`OdNrKmA|o@~p@hDBlXb^rc@~DaE{@f\\rh@jo@dSmi@pRe~B|h@izBmHk]jZqaCt]hOrf@cr@`[d]rKaCxD{Y|JZdXos@Xg[zFCzByq@ja@cSqE{dArPmj@`OyG{CqcAzEMhBud@pKeTh_A}l@lCfRnh@gVjSlo@hEoGvHzd@hmA{p@p~@aoBxDd\\rLl@M{`@nEeBmLiKcUqxA~u@saDTis@gj@}hChe@yJiTgPxQkn@s|AxJsYva@ss@b`@eLqJaHilAko@g|Ay{BvsAuRua@|@ig@aYu`AuEnG}LaUyWjOgMwIkX`HeFeW_S{Bk@fQ{NsD_CefA{PyUZ_^yIoLjIuNpi@`NzL_eBaNvAnE{oA}MsItCkWyRtAoVws@{G_u@~D}CwIka@uKvIqC{PbKkIgCeXiPvEuTufAa\\|o@wYfIxDpUeGxBnD_~AaQfM{I_q@{d@gi@oMpRgFoHy@dLpCsl@yHsd@`EePiLqQbLiB}Bw[eNsBu@zPeYpPr@eMioB_^uFziAmIyM_\\lBaChc@uaFg`A?naBvKpt@yJvv@a}@_Osd@zwEdPv[kQbh@pDjUqi@dbASfh@ca@nXuJxp@gi@rWsDt^qq@bbA{y@zhCqVjVc\\xxDyRfOeD|Y"],"DIFF":[]},"rada_komitety":null,"wskazniki":null,"radni_powiazania":null,"szef":null,"ostatnie_posiedzenie":null,"dzielnice":null,"dataset":null}}}