{"object":{"id":"860840","dataset":"gminy","object_id":"1451","data":{"powiaty.sejm_okreg_id":"11","nazwa_urzedu":"Urz\u0105d Gminy w Ostr\u00f3wku","wydatki_roczne":"14347876.91","teryt":"101706","id":"1451","powierzchnia":"101.00","nts":"1101817062","szef_stanowisko_id":"3","nazwa":"Ostr\u00f3wek","zadluzenie_roczne":"893548.02","dochody_roczne":"13454328.89","powiaty.nazwa":"wielu\u0144ski","fax":"0-43 841-50-26","adres":"98-311 Ostr\u00f3wek","wojewodztwa.id":"5","telefon":"0-43 841-50-23","typ_nazwa":"Gmina wiejska","powiat_id":"343","wojewodztwa.nazwa":"\u0141\u00f3dzkie","bip_www":"www.ostrowek.asi.pl","liczba_ludnosci":4611,"typ_id":"2","wojewodztwo_id":"5","email":"asi@asi.pl","powiaty.id":"343","rada_nazwa":"Rada Gminy Ostr\u00f3wek"},"score":1,"layers":{"enspat":{"ADD":["uzrxHcfhpBhe@_H|Yz{Cfp@e\\nJbFeAdYfqCscAtVvgCnl@gWhP~bBpHFyGwq@d[eKo^iwDlfCmpArBg}@iFaj@rR}BoDij@jOI~@{JbR`HtC_MaEieAmE}A~Jco@sD}jA`Fei@h[aSng@qv@cE}z@zKucATirA{FF{Kyz@{vBk}@olAmdHcW}XwJyx@uVfh@wa@gAa\\f_@of@fxArI~RaTdzAyq@tPwGbb@oO`b@zn@x}Age@vNwW``AjLtMtE|y@gg@nxCwEhuA}zA~^{CfMbTpg@`B|dA|UxTar@l{B}GxkA"],"DIFF":[]},"rada_komitety":null,"wskazniki":null,"radni_powiazania":null,"szef":null,"ostatnie_posiedzenie":null,"dzielnice":null,"dataset":null}}}