{"object":{"id":"860857","dataset":"gminy","object_id":"1469","data":{"powiaty.sejm_okreg_id":"16","nazwa_urzedu":"Gmina Pacyna","wydatki_roczne":"10053715.64","teryt":"140403","id":"1469","powierzchnia":"90.00","nts":"1142504032","szef_stanowisko_id":"3","nazwa":"Pacyna","zadluzenie_roczne":"427789.69","dochody_roczne":"9625925.95","powiaty.nazwa":"gostyni\u0144ski","fax":"0-24 285-80-64","adres":"ul. Ignacego \u0141ukasiewicza 7\n09-541 Pacyna","wojewodztwa.id":"7","telefon":"0-24 285-80-54","typ_nazwa":"Gmina wiejska","powiat_id":"70","wojewodztwa.nazwa":"Mazowieckie","bip_www":"bip.pacyna.mazowsze.pl\/","liczba_ludnosci":3819,"typ_id":"2","wojewodztwo_id":"7","email":"gmina@pacyna.mazowsze.pl","powiaty.id":"70","rada_nazwa":"Rada Gminy Pacyna"},"score":1,"layers":{"enspat":{"ADD":["atp~HkodwBb_BpHkCvaCnx@eo@xzArTeAz~@jc@hcCv_@lk@cX~f@fCvGpiCja@_EvR|iAjKqH_kBxPqP~bAl~@rKgs@jc@uMtNcuAmJ{`CmX}_CaSpb@mr@y`Aen@i[|_AkzDv{@uk@{Ncf@gKmgBlCye@}Myn@qg@qeAhCsE{R}m@wMpTyVoAbC}}Ac~AvmBmv@{QfDkf@ql@kPuEvb@ukAkQu\\dpAiN|lA{NlS`UbtAyxArh@vRffAbLcGnG|sAaj@oJi`Anb@sEhaE"],"DIFF":[]},"rada_komitety":null,"wskazniki":null,"radni_powiazania":null,"szef":null,"ostatnie_posiedzenie":null,"dzielnice":null,"dataset":null}}}