{"object":{"id":"860859","dataset":"gminy","object_id":"1471","data":{"powiaty.sejm_okreg_id":"23","nazwa_urzedu":"Urz\u0105d Gminy Padwa Narodowa","wydatki_roczne":"17704105.43","teryt":"181106","id":"1471","powierzchnia":"71.00","nts":"3183611062","szef_stanowisko_id":"3","nazwa":"Padew Narodowa","zadluzenie_roczne":"2224705.64","dochody_roczne":"15479399.79","powiaty.nazwa":"mielecki","fax":"0-15 811-93-80","adres":"39-340 Padew Narodowa 212","wojewodztwa.id":"9","telefon":"0-15 811-93-27","typ_nazwa":"Gmina wiejska","powiat_id":"168","wojewodztwa.nazwa":"Podkarpackie","bip_www":"www.biuletyn.net\/nt-bin\/start.asp?podmiot=padewnarodowa\/","liczba_ludnosci":5424,"typ_id":"2","wojewodztwo_id":"9","email":"zusugp@ptc.pl","powiaty.id":"168","rada_nazwa":"Rada Gminy w Padwi Narodowej"},"score":1,"layers":{"enspat":{"ADD":["wqesHevbbCpMbnD`Qrk@xg@jYzhB{s@zf@zD|m@rkAl{AtlFbq@yWxHya@xZvDpCcP`BcVgWaSz@qVwQm_@hNkWu@aPq\\_NlEiNcLwRnDqOh\\kh@fI~Mf`@wj@`h@jh@bBs[dEv@lHds@dEi`@hKlH~Ke^yRHxEavAsHy[kPiMp@eV{OwKPiVdEn@_D}YbIgWxRuHbCo^tL|GrAiVaO_UdGkWyE}d@|k@g@pLkVwZabBda@uT~`@|{@`Ke^d[vHGonAaKwd@l~@ejApOuaAiGow@gv@syAz@vb@qj@zt@kNlz@lGjO}Sfg@mQnnAi[_@mf@mu@mC|_@k}Amz@wo@{I_Kd`AosAnpC{UvHwRmMax@nGrRbp@eH]qa@b}@|DtZo^xRlLzQaMtJLzKeUrD}Y}[Dt`@`KbMaVvYf@hJqX~Xsr@lP"],"DIFF":[]},"rada_komitety":null,"wskazniki":null,"radni_powiazania":null,"szef":null,"ostatnie_posiedzenie":null,"dzielnice":null,"dataset":null}}}