{"object":{"id":"860862","dataset":"gminy","object_id":"1474","data":{"powiaty.sejm_okreg_id":"21","nazwa_urzedu":"Urz\u0105d Gminy Pakos\u0142awice","wydatki_roczne":"10563017.89","teryt":"160708","id":"1474","powierzchnia":"74.00","nts":"5163107082","szef_stanowisko_id":"3","nazwa":"Pakos\u0142awice","zadluzenie_roczne":"-796759.55","dochody_roczne":"11359777.44","powiaty.nazwa":"nyski","fax":"(077) 4357614","adres":"48-314 Pakos\u0142awice 1","wojewodztwa.id":"8","telefon":"(077) 4357614","typ_nazwa":"Gmina wiejska","powiat_id":"194","wojewodztwa.nazwa":"Opolskie","bip_www":"bip.pakoslawice.pl\/","liczba_ludnosci":3765,"typ_id":"2","wojewodztwo_id":"8","email":"ug@pakoslawice.pl","powiaty.id":"194","rada_nazwa":"Rada Gminy Pakos\u0142awice"},"score":1,"layers":{"enspat":{"ADD":["k`wsH}vghBnUuNzB|ZwL|DMhKp^pFqXhhDbUrF`IwNtBobAbNu\\tQ|JkL~l@r\\h@di@we@f[dHfZfu@xj@eAlPcNjNerAzUki@xu@{Tz@|Ihg@_EyKczAxTqGoE{mFj`@dEwLobA~Ak|@iHqSF}_@o[ol@uLuk@oDs|@~Ky\\oJe}@pMajA{d@xNVoJkN`CmBiq@pZmMwDqf@rGwSvLzB}FuZrfAsY~Od`@n`@}HwRca@cK_AqPuxB_b@iw@cNmRc_Az_@oCue@yQ{NuOzv@i\\mWyJdFmb@n`CrXpaAiNLoLjTcBff@|OtoBsf@cTaApyCgRuC{o@reBk@pm@aq@tr@rb@`aB{]~s@{k@xaCqEpEhEnfB}LpkA"],"DIFF":[]},"rada_komitety":null,"wskazniki":null,"radni_powiazania":null,"szef":null,"ostatnie_posiedzenie":null,"dzielnice":null,"dataset":null}}}