{"object":{"id":"860951","dataset":"gminy","object_id":"1563","data":{"powiaty.sejm_okreg_id":"21","nazwa_urzedu":"Urz\u0105d Gminy Polska Cerkiew","wydatki_roczne":"20247742.52","teryt":"160305","id":"1563","powierzchnia":"60.00","nts":"5163203052","szef_stanowisko_id":"3","nazwa":"Polska Cerekiew","zadluzenie_roczne":"3652317.10","dochody_roczne":"16595425.42","powiaty.nazwa":"k\u0119dzierzy\u0144sko-kozielski","fax":"0-77 487-51-50","adres":"47-260 Polska Cerkiew ul Raciborska 4","wojewodztwa.id":"8","telefon":"0-77 487-51-50","typ_nazwa":"Gmina wiejska","powiat_id":"102","wojewodztwa.nazwa":"Opolskie","bip_www":"www.bip.polskacerkiew.pl","liczba_ludnosci":4413,"typ_id":"2","wojewodztwo_id":"8","email":"biuro@aro.pl","powiaty.id":"102","rada_nazwa":"Rada Gminy  Polska Cerekiew"},"score":1,"layers":{"enspat":{"ADD":["y}xqHwqrmBvJhFfGdl@dKzAn^dDfO``@jQUzX~r@ri@}Gvl@dc@zCze@hr@bbAjBqHvL`p@~YmqAzYb\\yBj_@x`@yHfP|Iv`BjhCt~@~Fhb@}q@_FqK`WmQwDiLhLiXcVkm@{@k]wEJwJylBoSsC~L}JrQhOj]}PnTih@um@amAmZlMg_@cpAn]}ZuGmXdGsTg{@ahBnEac@{YxAa{@dp@qv@o`@}z@|JEgr@gIlAcHq`@aY`g@uc@en@xGyOkn@u`@wLpFcUhk@wBrb@cc@pbAg_@uHkAei@kL_JiIxdAwUxs@`LnIu^bgD"],"DIFF":[]},"rada_komitety":null,"wskazniki":null,"radni_powiazania":null,"szef":null,"ostatnie_posiedzenie":null,"dzielnice":null,"dataset":null}}}