{"object":{"id":"861001","dataset":"gminy","object_id":"1612","data":{"powiaty.sejm_okreg_id":"22","nazwa_urzedu":"Urz\u0105d Miejski w Przemy\u015blu","wydatki_roczne":"476697351.22","teryt":"186201","id":"1612","powierzchnia":"46.00","nts":"3183462011","szef_stanowisko_id":"2","nazwa":"Przemy\u015bl","zadluzenie_roczne":"44130594.60","dochody_roczne":"432566756.62","powiaty.nazwa":"Przemy\u015bl","fax":"0-16 678-64-49","adres":"Przemy\u015bl, Rynek 1 37-700 Przemy\u015bl","wojewodztwa.id":"9","telefon":"0-16 678-68-20","typ_nazwa":"Gmina miejska","powiat_id":"241","wojewodztwa.nazwa":"Podkarpackie","bip_www":"www.przemysl.pl\/bip","liczba_ludnosci":65000,"typ_id":"1","wojewodztwo_id":"9","email":"mail@um.przemysl.pl","powiaty.id":"241","rada_nazwa":"Rada Miejska w Przemy\u015blu"},"score":1,"layers":{"enspat":{"ADD":["uasnHqi_jCqZgb@kGcsAiQuh@PkfAyNDzDcZaNFyEaUsfAa[nUy|Bo~@wV}d@fA`Dgj@mEd@mIl@gBfgAyp@px@hGh`@mItWhAfl@jNfvAcP~Yo]xHuJh^yLkeAkO{Us^vaA_F`kBtWj[cFtjAlFAi@lYuIhv@cN~CyHf\\aAzKiTkD{Mp_B`WzJbNch@fq@mGbEoJtyAzdAt[}g@tId@tMrv@zNbOzOaEeMof@~A{R~]_Fk@af@|Rx@hHxd@tJlDyEfo@b\\nt@zVbDnWgXxTgE`Wid@mWuXse@uNoFws@jf@ulB~MgDnG{u@jUgx@"],"DIFF":[]},"rada_komitety":null,"wskazniki":null,"radni_powiazania":null,"szef":null,"ostatnie_posiedzenie":null,"dzielnice":null,"dataset":null}}}