{"object":{"id":"861037","dataset":"gminy","object_id":"1649","data":{"powiaty.sejm_okreg_id":"23","nazwa_urzedu":"Urz\u0105d Gminy Pysznica","wydatki_roczne":"26325658.09","teryt":"181803","id":"1649","powierzchnia":"147.00","nts":"3183618032","szef_stanowisko_id":"3","nazwa":"Pysznica","zadluzenie_roczne":"997912.67","dochody_roczne":"25327745.42","powiaty.nazwa":"stalowowolski","fax":"0-15 841-00-17","adres":"Pysznica, Ul. Wolno\u015bci 277 37-403 Pysznica","wojewodztwa.id":"9","telefon":"0-15 841-00-04","typ_nazwa":"Gmina wiejska","powiat_id":"288","wojewodztwa.nazwa":"Podkarpackie","bip_www":"www.pysznica.bip.info.pl","liczba_ludnosci":10177,"typ_id":"2","wojewodztwo_id":"9","email":"ug@pysznica.pl","powiaty.id":"288","rada_nazwa":"Rada Gminy Pysznica"},"score":1,"layers":{"enspat":{"ADD":["qlgtHeqcfChQf_@fm@`ItGr`@ld@`_AeErc@~Ij`Ao@zr@sKrh@{B||@|^dk@`k@yo@tTi@xX}Vhk@zYfIqDDj|@l]vd@q_@lToKnVrGtFjBj_A|l@sXlo@w{Abk@qH\\cUt\\tK`e@aUrh@_w@tEik@fd@iPeDoj@pEkIlZtU|y@s^Z|]bX`LxqAZh\\iy@eSgIm[bKmMw_@z]}RaJ_qAdLs@~BkoBs\\uf@zYyTjIge@naAhNhm@kt@ug@keAaNz\\dDdRsKaJJe[hOeJ{Yef@dEer@cO}ClMu[y@{UsJoH`GsNs_@g|@jBoN}O_NtDga@eI_g@qHDaq@fJgB_m@yg@tAxTjzCnHg@|AtRrX}Fv@x[{n@|N_Gex@uZpKse@aeGsv@jAiAsWmQwAwc@xKqOju@eI}QjTqr@ucAy_AgRt`AmHyEgIlY?zfBgU|JyE``@{S`WxQ`bDmNVmSuzA_I?gNua@dHs\\wGyEpHpCdGaXaDw|AcIsGs@yX{v@qCwoAvrA{c@`Fkk@fy@sMxx@sXvn@eBtr@hM`u@yJjYa@f|AaSvpD"],"DIFF":[]},"rada_komitety":null,"wskazniki":null,"radni_powiazania":null,"szef":null,"ostatnie_posiedzenie":null,"dzielnice":null,"dataset":null}}}