{"object":{"id":"861068","dataset":"gminy","object_id":"1681","data":{"powiaty.sejm_okreg_id":"16","nazwa_urzedu":"","wydatki_roczne":"11163587.74","teryt":"141304","id":"1681","powierzchnia":"99.00","nts":"1142513042","szef_stanowisko_id":"3","nazwa":"Radzan\u00f3w","zadluzenie_roczne":"-73437.00","dochody_roczne":"11237024.74","powiaty.nazwa":"m\u0142awski","fax":"","adres":"","wojewodztwa.id":"7","telefon":"","typ_nazwa":"Gmina wiejska","powiat_id":"174","wojewodztwa.nazwa":"Mazowieckie","bip_www":"","liczba_ludnosci":3615,"typ_id":"2","wojewodztwo_id":"7","email":"","powiaty.id":"174","rada_nazwa":"Rada Gminy Radzan\u00f3w"},"score":1,"layers":{"enspat":{"ADD":["cumbI{k}yB|GtUzb@g@|[dUh^wOlTha@pAt\\gY~m@iAf[jXdlAvUjF|Gnh@em@lxAp^dgAwKnYc\\uGmKlb@zEx[hQ`c@dBxq@tw@zk@aEtaAhXn@t@a_@Trd@xQqOqK}]sZaYn\\oP`nAiMrCda@eJ~BxLnQ`y@}c@raA|h@lQixAdx@DnHck@z\\}Q`{@tk@a\\coCyKwsCyLo[}u@_YlRo\\pOuDArU|`@da@pa@lENe]lx@j\\kCto@dqAeQxp@_^cUufBuTqE_@mL}S_Icd@_u@mCwq@`U_u@{KyYqm@`WmYlm@i_@~Sgg@iu@lA_IyR}JkEuvBweBmlBnSuo@cd@aUoUbEq@sc@}Sx@kBwaAk]rIDacCug@sQef@_lAcQ{EiA`oAcyAgSmTtsBnt@hw@gAlp@i\\xpAcTpQuFkReW|i@|Avu@m]~h@uHflAnHln@{_@`Y"],"DIFF":[]},"rada_komitety":null,"wskazniki":null,"radni_powiazania":null,"szef":null,"ostatnie_posiedzenie":null,"dzielnice":null,"dataset":null}}}