{"object":{"id":"861146","dataset":"gminy","object_id":"1757","data":{"powiaty.sejm_okreg_id":"16","nazwa_urzedu":"","wydatki_roczne":"9436938.41","teryt":"142806","id":"1757","powierzchnia":"73.00","nts":"1143028062","szef_stanowisko_id":"3","nazwa":"Rybno","zadluzenie_roczne":"-438357.63","dochody_roczne":"9875296.04","powiaty.nazwa":"sochaczewski","fax":"","adres":"","wojewodztwa.id":"7","telefon":"","typ_nazwa":"Gmina wiejska","powiat_id":"283","wojewodztwa.nazwa":"Mazowieckie","bip_www":"","liczba_ludnosci":3463,"typ_id":"2","wojewodztwo_id":"7","email":"","powiaty.id":"283","rada_nazwa":"Rada Gminy Rybno"},"score":1,"layers":{"enspat":{"ADD":["awc~Him}yBrJ~JrEkWbLrK{Ihk@bDf_@oI{IeG~\\`BtlC`d@~_@al@niEvRvJzEi]phAlw@nLaB`b@vj@qEvEzUbr@q}@pcAiOlCoCfv@zLvu@xhAj@hYwyCdcAh[pg@qkDpOgq@n[ol@jtErkBlbApEhBw^|UyEdn@m_AiMqz@qk@oHop@qd@kQo|DrO}{BsJsQ`QsbAw_AciBqP`I{Mjf@mo@iC`H~z@wrAoMu~@nc@ohAmX{]tM{GaIut@p{BkxBacBrAoNkPyMK|h@sMrz@"],"DIFF":[]},"rada_komitety":null,"wskazniki":null,"radni_powiazania":null,"szef":null,"ostatnie_posiedzenie":null,"dzielnice":null,"dataset":null}}}