{"object":{"id":"861224","dataset":"gminy","object_id":"1836","data":{"powiaty.sejm_okreg_id":"12","nazwa_urzedu":"Urz\u0105d Gminy Siepraw","wydatki_roczne":"28208436.10","teryt":"120906","id":"1836","powierzchnia":"32.00","nts":"2122009062","szef_stanowisko_id":"3","nazwa":"Siepraw","zadluzenie_roczne":"3945178.15","dochody_roczne":"24263257.95","powiaty.nazwa":"my\u015blenicki","fax":"(012) 37-21-806","adres":"32-447 Siepraw 1","wojewodztwa.id":"6","telefon":"(012) 37-21-811","typ_nazwa":"Gmina wiejska","powiat_id":"180","wojewodztwa.nazwa":"Ma\u0142opolskie","bip_www":"www.wrotamalopolski.pl\/root_BIP\/BIP_w_Malopolsce\/gminy\/root_Siepraw\/Wprowadzenie\/","liczba_ludnosci":8236,"typ_id":"2","wojewodztwo_id":"6","email":"gmina@siepraw.pl","powiaty.id":"180","rada_nazwa":"Rada Gminy Siepraw"},"score":1,"layers":{"enspat":{"ADD":["kgwoHym}xBlQt[tHd{@ne@ln@oOfaBpQhUjTxCxIzd@xc@oJjYn[vKgAa@u[lFcEyFwFnBwkAtk@gJvN`U|@w{@tn@en@fOa_CnWm\\n[iaBbQkQ}A{j@}@cW}Lj@wDeg@qUoSyWssA_[p]^lOa^zMuTmk@_FjFqQq`AaSvn@iZeDz@xo@_WxUu`@hArTvG`Qhy@nWhUyQwE{Ntc@ub@|`@_h@mB}l@j`@wAh`C"],"DIFF":[]},"rada_komitety":null,"wskazniki":null,"radni_powiazania":null,"szef":null,"ostatnie_posiedzenie":null,"dzielnice":null,"dataset":null}}}