{"object":{"id":"861311","dataset":"gminy","object_id":"1922","data":{"powiaty.sejm_okreg_id":"29","nazwa_urzedu":"Urz\u0105d Miejski w So\u015bnicowicach","wydatki_roczne":"0.00","teryt":"240506","id":"1922","powierzchnia":"116.00","nts":"2244705063","szef_stanowisko_id":"1","nazwa":"So\u015bnicowice","zadluzenie_roczne":"0.00","dochody_roczne":"0.00","powiaty.nazwa":"gliwicki","fax":"0-32 238-75-50","adres":"So\u015bnicowice, Ul. Rynek 19 44-153 So\u015bnicowice","wojewodztwa.id":"12","telefon":"0-32 238-71-91","typ_nazwa":"Gmina miejsko-wiejska","powiat_id":"60","wojewodztwa.nazwa":"\u015al\u0105skie","bip_www":"sosnicowice.i-gmina.pl","liczba_ludnosci":8533,"typ_id":"3","wojewodztwo_id":"12","email":"um@sosnicowice.pl","powiaty.id":"60","rada_nazwa":"Rada Miejska So\u015bnicowice"},"score":1,"layers":{"enspat":{"ADD":["sxjqHmvyoBwe@|EzB~y@_h@hKnAoXeKjGaJfdAtEhj@{eAkp@qTVmIly@avApDsp@viA}C|tBemA~a@Ycc@sb@_Ioa@va@uYzbBtIjkAgq@wa@k^sq@}o@jSgSp^gl@i{CsO{AiMwlArJ_QsOo`AqScTc[uDlPojBeHgdAeNzIaLmV@k^kW_h@bi@{GsGcmDvD_Os]sGai@rHwIqMjAuWkM{S}@q`@lTyUeHkSvt@a`AjSntApTitBtIlApK{[fIqnBzMqXlA{[fKmCbZjb@dr@LxJlf@QhnAtBxIzMoJ~vAzGlqAx_@vD_Tpw@xf@sA{\\qL}LlFsZyb@_`@tM{_BbeAnv@vj@hP|UaWf_@tG|M{KlMtQtBx^iI|s@fEzc@{Z`GcSmp@mOlF`InlB_QjPa@~Y{QlHlOzO{SlYdJp^cCrJxF\\kCbJiH{JaNvXvXsCyDj\\uJn@pBpqAvZjSbLaLhKnPdMm]tHhExEu\\lcAjFiGjzAzv@d`@dEm\\bPiIBlf@bPnCpMcUlm@xv@"],"DIFF":[]},"rada_komitety":null,"wskazniki":null,"radni_powiazania":null,"szef":null,"ostatnie_posiedzenie":null,"dzielnice":null,"dataset":null}}}