{"object":{"id":"859584","dataset":"gminy","object_id":"196","data":{"powiaty.sejm_okreg_id":"39","nazwa_urzedu":"Urz\u0105d Miasta i Gminy Buk","wydatki_roczne":"40570281.60","teryt":"302103","id":"196","powierzchnia":"91.00","nts":"4306121033","szef_stanowisko_id":"1","nazwa":"Buk","zadluzenie_roczne":"-335428.03","dochody_roczne":"40905709.63","powiaty.nazwa":"pozna\u0144ski","fax":"0-61 814-06-71","adres":"64-320 Buk ul. Ratuszowa 1","wojewodztwa.id":"15","telefon":"0-61 814-06-71","typ_nazwa":"Gmina miejsko-wiejska","powiat_id":"235","wojewodztwa.nazwa":"Wielkopolskie","bip_www":"bip.buk.gmina.pl","liczba_ludnosci":12230,"typ_id":"3","wojewodztwo_id":"15","email":"informatyk@buk.gmina.pl","powiaty.id":"235","rada_nazwa":"Rada Miasta i Gminy Buk"},"score":1,"layers":{"enspat":{"ADD":["a`|~HkyjdBrGjp@fE`bAgD`rAlfAiIzQqd@xmBf{BdFru@_UpMwe@mB_Vzb@zMp{Bwj@pc@_W^qC~f@vu@tSzC~_@dt@mPfMltChl@|^iVh|AfDh_@njAfWvTjXbQ_aBlLpSva@aX`[yoA~UcyBzUwu@f`BtuA`JuXlf@nEn`@x`BzRvOdNhsAnViPkKcSbRmpAeAeSeNgDzDozArlAoCfg@zOfc@pi@`Ka\\cIcJpe@kz@u[{DByzDqVofA_E}cAgPm\\qP{Fue@fN_Hdg@eLsBsHfUcWdCtAl}@_nA`p@cJavBo[oDsFg`@aTeB_Uw^on@vIqWef@hXezAkr@pLcu@ii@}Jal@~EcXz\\mt@AoX|MoGfTgi@sLxIk[wOa{@ZafFb|BwcAK{^iUcR`Z"],"DIFF":[]},"rada_komitety":null,"wskazniki":null,"radni_powiazania":null,"szef":null,"ostatnie_posiedzenie":null,"dzielnice":null,"dataset":null}}}