{"object":{"id":"861405","dataset":"gminy","object_id":"2016","data":{"powiaty.sejm_okreg_id":"13","nazwa_urzedu":"Urz\u0105d Gminy Su\u0142oszowa","wydatki_roczne":"16493265.70","teryt":"120613","id":"2016","powierzchnia":"53.00","nts":"2122006132","szef_stanowisko_id":"3","nazwa":"Su\u0142oszowa","zadluzenie_roczne":"-1083045.30","dochody_roczne":"17576311.00","powiaty.nazwa":"krakowski","fax":"(12) 3896028 wew. 29","adres":"32-045 Su\u0142oszowa I 80","wojewodztwa.id":"6","telefon":"(12) 3896028","typ_nazwa":"Gmina wiejska","powiat_id":"122","wojewodztwa.nazwa":"Ma\u0142opolskie","bip_www":"www.wrotamalopolski.pl\/root_BIP\/BIP_w_Malopolsce\/gminy\/root_Suloszowa\/Wprowadzenie\/","liczba_ludnosci":5828,"typ_id":"2","wojewodztwo_id":"6","email":"gmina@suloszowa.pl","powiaty.id":"122","rada_nazwa":"Rada Gminy w Su\u0142oszowej"},"score":1,"layers":{"enspat":{"ADD":["md_rH}dgwBxHrt@fRz]cOfr@zDfq@hz@_]j\\Yvc@`\\jy@qCxLkJpRa_Al]_zBfw@ibBv`@dJfVm_AdNX|Mco@eXtErHw[y_@kxA`a@ij@}b@ib@mDnL_L}Wrx@q`BvH|CcCzXnN|BlVmeA`LjNlJqKcEe^vYo`@sBap@tTi_A`GyyAw`@`KcI|TaF}EoNn`@wx@~q@ca@_Vge@nz@oCmL`_@icCquAw@o`@{BuO`l@yYnLqLhn@e^|P_AfKdw@r~@sI`h@cPjMnA|XzPG{Er{Am\\yQoj@hgCgKrSaYgRyNhc@jSjWmX|jB}BvaB{QzKgUdq@"],"DIFF":[]},"rada_komitety":null,"wskazniki":null,"radni_powiazania":null,"szef":null,"ostatnie_posiedzenie":null,"dzielnice":null,"dataset":null}}}