{"object":{"id":"861430","dataset":"gminy","object_id":"2041","data":{"powiaty.sejm_okreg_id":"32","nazwa_urzedu":"Urz\u0105d Miasta i Gminy Szczekociny","wydatki_roczne":"22440693.26","teryt":"241608","id":"2041","powierzchnia":"134.00","nts":"2245016083","szef_stanowisko_id":"1","nazwa":"Szczekociny","zadluzenie_roczne":"-344880.72","dochody_roczne":"22785573.98","powiaty.nazwa":"zawiercia\u0144ski","fax":"0-34 355-71-65","adres":"Szczekociny, Ul. Senatorska 2 42-445 Szczekociny","wojewodztwa.id":"12","telefon":"0-34 355-70-50","typ_nazwa":"Gmina miejsko-wiejska","powiat_id":"363","wojewodztwa.nazwa":"\u015al\u0105skie","bip_www":"www.bip.szczekociny.pl","liczba_ludnosci":8192,"typ_id":"3","wojewodztwo_id":"12","email":"umig@szczekociny.pl","powiaty.id":"363","rada_nazwa":"Rada Miasta i Gminy Szczekociny"},"score":1,"layers":{"enspat":{"ADD":["igrtHsf|wB|Anh@|p@nPkFbv@{MeDoFlzApd@ryB{NfgApIx`CqLvLbSb|@jFlAoDeLbCqFdC`K~I{YfVwBq@{JvScKlBnGvBeW~NsGlAwOpYcK|Co`@zHmHwEqAbDqZrw@sd@lWudAfIoDj@eNsAy@fKgFrIeUiUsJ`G}UrMgVhb@gM|Cg\\dz@f[aJhTbc@nc@}Rzp@jThLoAvaArr@~[eFfTdr@f_@sDnQ~_@`Pd@_Zn\\jGpBqa@hKkFvtC`B`aAmJ~h@dON_LrRsFdRy]~HbGoP|n@`d@x`ApgAtu@xi@wpA`MdFbJkSzIjLxE{LyDqE~Car@oRqi@`Dm]}Z{n@bR}e@nWiN{DiLcHfRuU_EeGkRhb@k\\cD{k@_wAyE`Qs|@WaZ}j@ynAu~@{r@aGq^i\\{_@uQqk@{[hGoKkTgtAog@SyQ}g@sRsP_]|Lg[kJ[hAcX~TutAfHovAi^gGbG_Wk_Aia@rB{Nyf@eUvFe`@e^oJeO`lAva@`bCcHe@aMbZsRuEa@nTcJ_BwIzk@~BtUnD{By@x{AaStaByIt]mCrd@aHwLyHp]k@ak@uUgf@w@hRkYkOuZns@wRuXjc@}dB}FoCdEmhAye@zk@aQKsa@iQyTggAw}@pI~PtvA}Adk@_fAxPkUtWfHt~@mG~qAaI|QxS`EqJfo@wa@qHkBtVosAqZ"],"DIFF":[]},"rada_komitety":null,"wskazniki":null,"radni_powiazania":null,"szef":null,"ostatnie_posiedzenie":null,"dzielnice":null,"dataset":null}}}