{"object":{"id":"861646","dataset":"gminy","object_id":"2257","data":{"powiaty.sejm_okreg_id":"16","nazwa_urzedu":"Urz\u0105d Gminy Wieczfnia Ko\u015bcielna","wydatki_roczne":"17999135.06","teryt":"141309","id":"2257","powierzchnia":"120.00","nts":"1142513092","szef_stanowisko_id":"3","nazwa":"Wieczfnia Ko\u015bcielna","zadluzenie_roczne":"-1116974.21","dochody_roczne":"19116109.27","powiaty.nazwa":"m\u0142awski","fax":"0-23 654-00-50","adres":"Wieczfnia Ko\u015bcielna , Ul. - 48 06 - 513 Wieczfnia Ko\u015bcielna","wojewodztwa.id":"7","telefon":"0-23 654-00-04, 0-23 654-00-36","typ_nazwa":"Gmina wiejska","powiat_id":"174","wojewodztwa.nazwa":"Mazowieckie","bip_www":"www.bip.wieczfnia.akcessnet.net","liczba_ludnosci":4268,"typ_id":"2","wojewodztwo_id":"7","email":"wieczfnia_koscielna@gminy.pl","powiaty.id":"174","rada_nazwa":"Rada Gminy Wieczfnia Ko\u015bcielna"},"score":1,"layers":{"enspat":{"ADD":["gw~cI_xz{BlzCrxEI~X~o@|r@nNkRlhBrjBbe@lzAbeA`e@pIqs@lb@`Anh@r^rMaaApSlNTqN`OhDzHeZkG{MhLsN~g@fYhHsf@|TonANy`@za@up@}Ton@ma@ghCbEcg@fd@we@rMefAzAe~Diw@iVhIit@oHg_@kUrE}v@_m@uq@q}Bqi@aRyp@xR_Nsc@rDga@eQ_PGkg@kK_a@i\\{ScTan@wcBmh@kQv]a_@_DcdCe_B~Dxp@jVja@zIpv@mBp[yh@hPkBz[dvAbpArKbl@gQtbAkJ_OcSf|Ar[tIrCye@`Z|`Aod@zqBic@{@bAvqEam@`qAyIeViTnc@"],"DIFF":[]},"rada_komitety":null,"wskazniki":null,"radni_powiazania":null,"szef":null,"ostatnie_posiedzenie":null,"dzielnice":null,"dataset":null}}}