{"object":{"id":"861695","dataset":"gminy","object_id":"2306","data":{"powiaty.sejm_okreg_id":"8","nazwa_urzedu":"Urz\u0105d Gminy i Miasta Witnica","wydatki_roczne":"55890837.84","teryt":"080107","id":"2306","powierzchnia":"279.00","nts":"4081301073","szef_stanowisko_id":"1","nazwa":"Witnica","zadluzenie_roczne":"8689787.81","dochody_roczne":"47201050.03","powiaty.nazwa":"gorzowski","fax":"0-95 751-52-18","adres":"66-460 Witnica ul. KRN 6","wojewodztwa.id":"4","telefon":"0-95 721-64-40","typ_nazwa":"Gmina miejsko-wiejska","powiat_id":"68","wojewodztwa.nazwa":"Lubuskie","bip_www":"www.bip.witnica.pl","liczba_ludnosci":13092,"typ_id":"3","wojewodztwo_id":"4","email":"admin@witnica.pl","powiaty.id":"68","rada_nazwa":"Rada Miejska w Witnicy"},"score":1,"layers":{"enspat":{"ADD":["gndaIws}yAnOri@`AniAlU_OnUz{ApoAit@jgAr|GolAxq@`Q|eAgf@pJkC|Pjp@bx@~Gd{@jOkCdNrOnyAo_AfI`[ny@aPdiCzg@pl@g@f{AhqAdu@lrApSnH_D~q@lMtQ~h@lSh}ArH~OiI|Etj@`KcF_CbrAbHsN~Yno@`McKpGx\\|H`@mIbh@wAlrC_P|IeKfzB|uAfRdf@}u@nN_BaJ}^lb@rWlh@sWuCal@rCiOfQeFaWgZbFgOeIaMdp@atAvWmD}Sq}Bwf@utCpM{eCeCed@eh@mwCorAclFW{PnXcT_E}LdIkNkFsEzSepBo[uxHl@c]s\\ubB}bB}jHnEqAsGaq@xLmFwJu_BiQqn@uQp^eZ`KaGvj@_Aqv@sRmJkY_uCm{@j\\jHpm@qj@pUv@va@mV_Bid@~Uce@vtBa`@{G}zAhl@kOqj@{b@hDyA}n@vQ{SyOacBoHza@y|@xEsNfJio@c}B`DpwAuIlJ|AjQjRoBdTxq@gQ|VZ~YkN|@jLrwAk^j_@r@ltA{`Avh@_Bhm@fEpo@hTpIwRdI|IpLvUo@vE~u@{E~g@jOo@eMjy@_[aVkFhIpCvQiJtxAhCuLxPxIqG~EzQxu@aQhf@ox@wWfJ_x@oWmnBkNzIkCpd@sGjFu`@}EyiAzq@xH~_@eJ`I{@rS"],"DIFF":[]},"rada_komitety":null,"wskazniki":null,"radni_powiazania":null,"szef":null,"ostatnie_posiedzenie":null,"dzielnice":null,"dataset":null}}}