{"object":{"id":"861700","dataset":"gminy","object_id":"2311","data":{"powiaty.sejm_okreg_id":"26","nazwa_urzedu":"Urz\u0105d Miasta W\u0142adys\u0142awowo","wydatki_roczne":"47268862.20","teryt":"221104","id":"2311","powierzchnia":"39.00","nts":"6224011041","szef_stanowisko_id":"1","nazwa":"W\u0142adys\u0142awowo","zadluzenie_roczne":"-4757323.06","dochody_roczne":"52026185.26","powiaty.nazwa":"pucki","fax":"0-58 674-07-63","adres":"84-120 W\u0142adys\u0142awowo ul. Gen. J. Hallera 19","wojewodztwa.id":"11","telefon":"0-58 674-54-00","typ_nazwa":"Gmina miejska","powiat_id":"245","wojewodztwa.nazwa":"Pomorskie","bip_www":"bip.wladyslawowo.pl","liczba_ludnosci":15296,"typ_id":"1","wojewodztwo_id":"11","email":"burms@wladyslawowo.pl","powiaty.id":"245","rada_nazwa":"Rada Miejska W\u0142adys\u0142awowa"},"score":1,"layers":{"enspat":{"ADD":["ubumIsysnBrR`sKiBvnEhRaFlCiW|\\d@{DaaAhdAiIiDmNfSmGn^ygJepAooAdNu]fE`HnMgj@fRsCmDsv@{Rph@mU|J}@}{EvO~Df@cVpa@?hU}d@to@gMfKwSzI_lAxOdIrFk^xMnIxM|i@tXBCwY|KbE~KcxAzOxDpDyi@cOqCfD{b@iOd@yGkc@z\\lBlKatAeGgF`XcE|FqgAsQgJoVpMwYqYwSxHoBmMuIbFuJiPnf@q~A|LcjAdm@szA`Eau@d_@os@v\\{tAvi@keDjPyL_OgU}lE|gQah@daBaRaPpCsIuDhK}OhvA{qAjsFkc@frAiw@tfA}b@fjAsIvqF"],"DIFF":[]},"rada_komitety":null,"wskazniki":null,"radni_powiazania":null,"szef":null,"ostatnie_posiedzenie":null,"dzielnice":null,"dataset":null}}}