{"object":{"id":"859622","dataset":"gminy","object_id":"234","data":{"powiaty.sejm_okreg_id":"17","nazwa_urzedu":"Urz\u0105d Gminy Chlewiska","wydatki_roczne":"16951624.31","teryt":"143001","id":"234","powierzchnia":"124.00","nts":"1142730012","szef_stanowisko_id":"3","nazwa":"Chlewiska","zadluzenie_roczne":"616200.78","dochody_roczne":"16335423.53","powiaty.nazwa":"szyd\u0142owiecki","fax":"0-48 628-72-71","adres":"26-510 Chlewiska ul. Czachowskiego 49","wojewodztwa.id":"7","telefon":"0-48 628-70-53","typ_nazwa":"Gmina wiejska","powiat_id":"306","wojewodztwa.nazwa":"Mazowieckie","bip_www":"www.chlewiska.asi.pl","liczba_ludnosci":6231,"typ_id":"2","wojewodztwo_id":"7","email":"asi@asi.pl","powiaty.id":"306","rada_nazwa":"Rada Gminy w Chlewiskach"},"score":1,"layers":{"enspat":{"ADD":["}gfxHimy}B|Nb]vZuIlKb`ApE{GpFvN|hA~TtP{w@ya@yM~Ca_@z{@aGnNy]a@rp@bSlGdWvg@rj@nE~C`ZzIYNhPrMpLfLeEoFfj@aQ{@RfXtPnLxj@~wAfA|W{WlwAgs@nh@iCxNtJoNtK|\\kCpYzQnLkAdSeIfDTrIrQYaIbt@zNeBrl@ro@cCfLh_@d`@Jpw@Fz`@yeApAwF`lA|v@Wf_@t_@p@h}B~MuB`@`QtGzA~VgN_BpXnNcWjh@sVfSgXzSqz@tScJxMwv@xTa^zCuv@bl@weCxO_BfQma@iHcm@pIlOtGgIcAtQhVm[dEvKnKucAhvAsI~NbR~WdfAhQhPbd@xBvo@g[jZjVxRsCyAsz@rHjKlFaYqoAoy@}]yb@oAsQ}ElQuZqc@rB{\\oj@yJcdAi`AzXyc@uVoz@wAklBmX_s@}_@cd@efBozCmaAwHs{@{k@yK}XBk\\iXs`@qdA}SqRmg@mSkIiIma@aMfAgHmN_MfSch@dDyIxT}NaCcWfQ|DpNgVkKmF`q@sT{QoFpGef@rtAi{@fyAy\\wn@sKdcA_Cve@uZb`AkAfb@"],"DIFF":[]},"rada_komitety":null,"wskazniki":null,"radni_powiazania":null,"szef":null,"ostatnie_posiedzenie":null,"dzielnice":null,"dataset":null}}}