{"object":{"id":"861738","dataset":"gminy","object_id":"2349","data":{"powiaty.sejm_okreg_id":"11","nazwa_urzedu":"Urz\u0105d Gminy Wr\u00f3blew","wydatki_roczne":"17672287.99","teryt":"101410","id":"2349","powierzchnia":"113.00","nts":"1101814102","szef_stanowisko_id":"3","nazwa":"Wr\u00f3blew","zadluzenie_roczne":"-2249983.61","dochody_roczne":"19922271.60","powiaty.nazwa":"sieradzki","fax":"0-43 821-34-15","adres":"Wr\u00f3blew, Ul. Wr\u00f3blew 15 98-285 Wr\u00f3blew","wojewodztwa.id":"5","telefon":"0-43 821-31-11","typ_nazwa":"Gmina wiejska","powiat_id":"273","wojewodztwa.nazwa":"\u0141\u00f3dzkie","bip_www":"www.wroblew.bip.cc","liczba_ludnosci":6138,"typ_id":"2","wojewodztwo_id":"5","email":"ugwroblew@bip.cc","powiaty.id":"273","rada_nazwa":"Rada Gminy Wr\u00f3blew"},"score":1,"layers":{"enspat":{"ADD":["aajzHmbipBtS|i@`NjiAdjAwKoTndB~C|p@~IpSjq@da@qEzd@pRbDzCuY`Vg@hQqa@nR`ZfsAiUxCcuAhq@lg@eNtdBle@fUvRsgCxn@|\\zi@mAv\\`Yzr@zMf_BpbBt@sQ~Deu@yEav@gHiR_y@}e@`IaVxE_hAta@e_@bc@fAj[cZ`n@agAhIo_AfLwTgXyKyFyx@fj@{@fAmNqUk^}\\ywB~f@qUuCsO~XwrA}]q_AsDe`BiQug@yk@ai@{V~`@iLds@dDtaAgmAv]{Vge@_jAzu@aOeHu@g`@aS|Aqg@ie@cGzMbCoe@aL}@yc@ffArC~cAmPxA_w@cGxGm`@qE}}@gc@tCmWgb@kj@q[_p@xrAvSrxArQlkA{`Azc@kDzY{g@oA_IbkCsXiMuCxa@uSdZyYjeAyDzt@"],"DIFF":[]},"rada_komitety":null,"wskazniki":null,"radni_powiazania":null,"szef":null,"ostatnie_posiedzenie":null,"dzielnice":null,"dataset":null}}}