{"object":{"id":"859434","dataset":"gminy","object_id":"47","data":{"powiaty.sejm_okreg_id":"33","nazwa_urzedu":"Urz\u0105d Gminy Bejsce","wydatki_roczne":"9835457.83","teryt":"260301","id":"47","powierzchnia":"57.00","nts":"3265303012","szef_stanowisko_id":"3","nazwa":"Bejsce","zadluzenie_roczne":"-25184.71","dochody_roczne":"9860642.54","powiaty.nazwa":"kazimierski","fax":"0-41 351-10-10 w.22","adres":"28-512 Bejsce","wojewodztwa.id":"13","telefon":"0-41 351-10-10 w.22","typ_nazwa":"Gmina wiejska","powiat_id":"101","wojewodztwa.nazwa":"\u015awi\u0119tokrzyskie","bip_www":"www.bip.gminy.com.pl\/bejsce","liczba_ludnosci":4324,"typ_id":"2","wojewodztwo_id":"13","email":"ugbejsce@gminy.com.pl","powiaty.id":"101","rada_nazwa":"Rada Gminy w Bejscach"},"score":1,"layers":{"enspat":{"ADD":["cdzqHify|BlRhVRfb@uI~PmBoIaBzVvIxmBrKnB_Ktf@lW`TvAtVpZDl`@`Tdm@hx@~PqKkD`]lu@c_Axe@`BYsPxO}LfBv_@kVl@~QtBkO~pAhv@_OiGfCkHhh@~X~Wtf@lApCjPgJvC^nOvNv@~M}g@zMzMtw@bA`@_SzQ_Q_SwyA~K}NsEiR~t@kMrb@gh@gPaeAwb@tE@{NwPyB_Eyh@wQyI~G}kAuZsCW{K~Wu_BcGyi@Jnh@uUcGLuRwe@u^`Fk\\`TfMhJyPuH_\\wX~Zx@gRyC{GfGoSaTsXfGuWub@w_@_U`]g`@}_AaOzf@cs@wYwk@pmAiXkVYrQk_@rCu@mW}h@ZgJyTqLpOnKjXcLvs@ua@wAhDltB{XvaA"],"DIFF":[]},"rada_komitety":null,"wskazniki":null,"radni_powiazania":null,"szef":null,"ostatnie_posiedzenie":null,"dzielnice":null,"dataset":null}}}