{"object":{"id":"859860","dataset":"gminy","object_id":"472","data":{"powiaty.sejm_okreg_id":"15","nazwa_urzedu":"Urz\u0105d Gminy Gd\u00f3w","wydatki_roczne":"46961172.00","teryt":"121902","id":"472","powierzchnia":"109.00","nts":"2122019022","szef_stanowisko_id":"3","nazwa":"Gd\u00f3w","zadluzenie_roczne":"835964.34","dochody_roczne":"46125207.66","powiaty.nazwa":"wielicki","fax":"0-12 251-40-05","adres":"32-420 Gd\u00f3w, ul. Rynek 40","wojewodztwa.id":"6","telefon":"0-12 251-41-66","typ_nazwa":"Gmina wiejska","powiat_id":"342","wojewodztwa.nazwa":"Ma\u0142opolskie","bip_www":"www.malopolska.pl\/BIP\/gdow","liczba_ludnosci":17041,"typ_id":"2","wojewodztwo_id":"6","email":"urzad@gdow.pl","powiaty.id":"342","rada_nazwa":"Rada Gminy Gd\u00f3w"},"score":1,"layers":{"enspat":{"ADD":["ukbpHesizBlQbGdr@aTje@t\\sSj}@fNzE~EyNrl@Y|DmXjUxL}CxHvLx@lJgSfCfKpQyEhEzS|~AhIkMrw@bNnc@jOy@cAjiArYdZtb@{a@dMvI}D~aBwMdTfDn\\gQi@m@bI@~WpGtGsBfu@p[`q@`Epr@ta@aGr@o_@bOcNbX|YlJ{LhRx@f@z[fOiAgF~\\fN_M~Ake@fScXxPzAhOc[vHhAmF}HzJoXgEe_AtJqO_MwIsC{p@zGP_@cTs[sd@qCui@zb@sQ~CkvAxFzDzCxy@rs@oCjDkJqM}\\{@a}A~\\nR|Fo`@zViQfDsl@_Fe|@zOeGfPsgAIcOyOqOlHuH`Gw}@cSuPCuRm\\iZqPrBiCkN}k@hDa~@maAkBmfBegAfKyRy[kJ}j@{WmUk@m\\c`@wFkl@uVvL|^pAp[qEjEaJeEsF{m@gSiPyWnTmOsGq]za@os@snAeLhFeAnc@w^_ZsUtOrE|VbKjeBqGzs@oLpS{@r_@i^kDoAxKrKx@nB~n@cJqHkgAdkCxB~g@oLnd@eC~p@{FBsBv^wOsUuOhmA}@lO"],"DIFF":[]},"rada_komitety":null,"wskazniki":null,"radni_powiazania":null,"szef":null,"ostatnie_posiedzenie":null,"dzielnice":null,"dataset":null}}}