{"object":{"id":"859864","dataset":"gminy","object_id":"476","data":{"powiaty.sejm_okreg_id":"17","nazwa_urzedu":"Urz\u0105d Gminy Gielni\u00f3w","wydatki_roczne":"11131667.95","teryt":"142302","id":"476","powierzchnia":"79.00","nts":"1142723022","szef_stanowisko_id":"3","nazwa":"Gielni\u00f3w","zadluzenie_roczne":"-605227.69","dochody_roczne":"11736895.64","powiaty.nazwa":"przysuski","fax":"48 672-00-04","adres":"Plac Wolno\u015bci 75, 26-434 Gielni\u00f3w","wojewodztwa.id":"7","telefon":"48 672-00-11","typ_nazwa":"Gmina wiejska","powiat_id":"243","wojewodztwa.nazwa":"Mazowieckie","bip_www":"www.bip.gielniow.akcessnet.net\/index.php?idg=1&id=1&x=1","liczba_ludnosci":4767,"typ_id":"2","wojewodztwo_id":"7","email":"gmina@gielniow.radom.pl","powiaty.id":"243","rada_nazwa":"Rada Gminy w Gielniowie"},"score":1,"layers":{"enspat":{"ADD":["gkbyHwlh|BbFnOpJcGdWlO|_@|hAhOf`BdJfIbBgKpYeB|Cx}@xWfTpT{SrKbO|f@ip@h}@tv@zNqQy@nNdSzX~Fnu@{FbWdDzw@w@lW}NtPuIkHiEdS`YxTrsAvYjNiJp[~q@`j@dNh_@h`@|f@oCZfMhImQbg@hp@vDp_@~Bk`@bp@uDcAoQfNiM|jAsPCwJeRKdX_|B~LePm@mp@d\\iA~@cmGkRso@_q@ehAyiDtj@Jy_AaZij@g[eHzb@s_Ea]dCq`@w^gE_aAch@e`@kd@|Aag@j`AhAl~@wj@hWdCpxAgi@faA_Ix_AkSzBRb{@k}BpSsx@ef@op@iiA_YzEmEd["],"DIFF":[]},"rada_komitety":null,"wskazniki":null,"radni_powiazania":null,"szef":null,"ostatnie_posiedzenie":null,"dzielnice":null,"dataset":null}}}