{"object":{"id":"859960","dataset":"gminy","object_id":"572","data":{"powiaty.sejm_okreg_id":"37","nazwa_urzedu":"Urz\u0105d Gminy Grodziec","wydatki_roczne":"19524677.08","teryt":"301002","id":"572","powierzchnia":"118.00","nts":"4305810022","szef_stanowisko_id":"3","nazwa":"Grodziec","zadluzenie_roczne":"143032.84","dochody_roczne":"19381644.24","powiaty.nazwa":"koni\u0144ski","fax":"0-63 248-55-00","adres":"Grodziec, Ul. G\u0142\u00f3wna 17 62-580 Grodziec","wojewodztwa.id":"15","telefon":"0-63 248-55-00","typ_nazwa":"Gmina wiejska","powiat_id":"116","wojewodztwa.nazwa":"Wielkopolskie","bip_www":"www.bip.grodziec.pl","liczba_ludnosci":5267,"typ_id":"2","wojewodztwo_id":"15","email":"ug@grodziec.pl","powiaty.id":"116","rada_nazwa":"Rada Gminy Grodziec"},"score":1,"layers":{"enspat":{"ADD":["u}_}Had{lBnH}@jDxZzNd@r]g\\xE|tCnWuDyCha@cPpJr@fQyPfF`h@zdAWfmC~aBq_AqCakCbfAjBwBkl@phBib@b_BbbAlYdw@|hD~sBrFwc@qCseBxRagDjUct@fRsvBpw@ucEx]uoFtF{hBah@e_@siAue@}a@co@sn@xC}bBc_@w~AjcB}NbVxN`Q_Y~XeKsk@_[rOoa@hz@oi@dQuZj\\aF{Kos@xWiLvReEu[mNfIqFuc@_RvI|TpbBhNmb@f]lZx@zlCsUgSws@vbBwAmNoHjIuB{Ig`B`t@vMpc@rIh|AqTvA{KjdA"],"DIFF":[]},"rada_komitety":null,"wskazniki":null,"radni_powiazania":null,"szef":null,"ostatnie_posiedzenie":null,"dzielnice":null,"dataset":null}}}