{"object":{"id":"860023","dataset":"gminy","object_id":"635","data":{"powiaty.sejm_okreg_id":"7","nazwa_urzedu":"Urz\u0105d Gminy Izbica","wydatki_roczne":"30770890.26","teryt":"060604","id":"635","powierzchnia":"138.00","nts":"3061006042","szef_stanowisko_id":"3","nazwa":"Izbica","zadluzenie_roczne":"4311593.82","dochody_roczne":"26459296.44","powiaty.nazwa":"krasnostawski","fax":"84 618-30-49","adres":"ul. Gminna 4,\n22-375 Izbica","wojewodztwa.id":"3","telefon":"84 618-30-34","typ_nazwa":"Gmina wiejska","powiat_id":"125","wojewodztwa.nazwa":"Lubelskie","bip_www":"www.bip.mbnet.pl\/enginev255.php?attr=bGFuZ2lkPTEmZ209MSZtaWQ9NiZzdHI9Ng==","liczba_ludnosci":8662,"typ_id":"2","wojewodztwo_id":"3","email":"ugizbica@mbnet.pl","powiaty.id":"125","rada_nazwa":"Rada Gminy Izbica"},"score":1,"layers":{"enspat":{"ADD":["kc}uHe{llCh@zJbN~@}DlAzGr^pOzEwBcInL}BVoNpLp_@qDyAxCpQwTjwCrCxaBiJjz@bXdXvEj\\qGtZbDp`@oU~d@kIno@hExp@n}@cXrRe[~dBpaArOfSnBz[yF~ZuVvN~BnzAf\\|cAjMzKlCsWbHjEhcAv}@`^{VeBgSnNqQzZsMhi@tQzVm`@du@maDnf@}a@d\\ojDtDxfAfd@h@vHmz@_Gk[sGmDwSrg@|Qm}AbN}HvE_m@{@q{@uIgZxCw{@yn@wbAwDyOpGqPoqC`U_WiIuTk_@vb@cWyCcOjPyp@~SgzBcJ_Zn]mZd~AeLdIe_AqJqbA{LoRcNagC_d@|@uXuv@mUdPqUq^mG}Gq\\nsAiXx`@g_@cg@uCgaA~Ew]oP}u@mc@yLqaAczAaCf\\c^ny@aKpfAip@vEoFxk@o]|`Awe@|]{Ij}@fOlRne@n@iWbg@gSlvAak@ngBmSxeB"],"DIFF":[]},"rada_komitety":null,"wskazniki":null,"radni_powiazania":null,"szef":null,"ostatnie_posiedzenie":null,"dzielnice":null,"dataset":null}}}