{"object":{"id":"859464","dataset":"gminy","object_id":"77","data":{"powiaty.sejm_okreg_id":"18","nazwa_urzedu":"Urz\u0105d Gminy Bielany \u017by\u0142aki","wydatki_roczne":"12083605.62","teryt":"142902","id":"77","powierzchnia":"110.00","nts":"1142629022","szef_stanowisko_id":"3","nazwa":"Bielany","zadluzenie_roczne":"341599.26","dochody_roczne":"11742006.36","powiaty.nazwa":"soko\u0142owski","fax":"(025) 787-80-13","adres":"ul. S\u0142oneczna 2; 08-311 Bielany","wojewodztwa.id":"7","telefon":"(025) 787-80-13","typ_nazwa":"Gmina wiejska","powiat_id":"284","wojewodztwa.nazwa":"Mazowieckie","bip_www":"www.bielany.bumsoft-2.pl\/","liczba_ludnosci":3806,"typ_id":"2","wojewodztwo_id":"7","email":"ugbielany@poczta.onet.pl","powiaty.id":"284","rada_nazwa":"Rada Gminy Bielany"},"score":1,"layers":{"enspat":{"ADD":["cmv~HgxrfCdk@`Orc@nm@pX~}@b@lt@zJdf@~x@|Alg@h\\z\\uCwDlt@rVhFu@n[w_@`|Boh@v}Abc@jfBvc@ls@wA`UrWl~BsBnVpJdMhg@aeBfyAgyBfWeMsPyzCdMoy@sKsfBlCi^|U}Wnl@jTfj@gAuNuh@@ct@fXcx@h]eIrPytA}YgVg[nNui@eKyJw_Av\\qvBkeAmRzKasBom@}e@zO{jA|SrKi@kkAjy@qThF}QiYi}AjYmOiGs^`Euf@sOsTxGudCyFgsAq{Arg@mReIw~@bTwCllAuIyTgc@jBwl@bXdDfUcv@i^oBoRe[_XiXxC`OhlAyBfjAlEl[mf@kBeIhdAmh@tdC_SzYkGpl@j_@nKhi@_OnNzLr_@aBh^vl@cRrBjCts@ijBtDnBhQe_@n@cCxg@tKnwC_Rlo@gPnF"],"DIFF":[]},"rada_komitety":null,"wskazniki":null,"radni_powiazania":null,"szef":null,"ostatnie_posiedzenie":null,"dzielnice":null,"dataset":null}}}